xia_module_gcp_project/__init__.py
xia_module_gcp_project/admin.py
xia_module_gcp_project/organization.py
xia_module_gcp_project/project.py
xia_module_gcp_project/templates/gcp-module-admin/base/main.tf
xia_module_gcp_project/templates/gcp-module-admin/module/main.tf
xia_module_gcp_project/templates/gcp-module-admin/module/variables.tf
xia_module_gcp_project/templates/gcp-module-organization/base/main.tf
xia_module_gcp_project/templates/gcp-module-organization/config/platform/gcp-org.yaml
xia_module_gcp_project/templates/gcp-module-organization/module/main.tf
xia_module_gcp_project/templates/gcp-module-organization/module/output.tf
xia_module_gcp_project/templates/gcp-module-organization/module/variables.tf
xia_module_gcp_project/templates/gcp-module-project/activate/main.tf
xia_module_gcp_project/templates/gcp-module-project/activate/variables.tf
xia_module_gcp_project/templates/gcp-module-project/base/activate.tf
xia_module_gcp_project/templates/gcp-module-project/base/main.tf
xia_module_gcp_project/templates/gcp-module-project/config/platform/gcp-project.yaml
xia_module_gcp_project/templates/gcp-module-project/module/main.tf
xia_module_gcp_project/templates/gcp-module-project/module/output.tf
xia_module_gcp_project/templates/gcp-module-project/module/variables.tf
xia_module_gcp_project-0.0.31.dist-info/LICENSE
xia_module_gcp_project-0.0.31.dist-info/METADATA
xia_module_gcp_project-0.0.31.dist-info/WHEEL
xia_module_gcp_project-0.0.31.dist-info/top_level.txt
xia_module_gcp_project-0.0.31.dist-info/RECORD
