Metadata-Version: 2.1
Name: xia-module-gcp-project
Version: 0.0.31
Requires-Python: >=3.9
License-File: LICENSE
Requires-Dist: PyYAML
Requires-Dist: xia-module
